pyvcmdline/__init__.py
pyvcmdline/__main__.py
pyvcmdline/cmdline_utils.py
pyvcmdline/const.py
pyvcmdline/json_prec.py
pyvcmdline/pyvcli_config.py
pyvcmdline/emb_demos/__init__.py
pyvcmdline/emb_demos/my_demo1.py
pyvcmdline/pyvcli_cogs/__init__.py
pyvcmdline/pyvcli_cogs/autogen_localctx.py
pyvcmdline/spare_parts/__init__.py
pyvcmdline/spare_parts/launch_game.py
pyvcmdline/spare_parts/launch_game0.py
pyvcmdline/spare_parts/launch_game1.py
pyvcmdline/spare_parts/network.py
pyvcmdline/template_0/cartridge/__init__.py
pyvcmdline/template_0/cartridge/gamedef.py
pyvcmdline/template_0/cartridge/pimodules.py
pyvcmdline/template_0/cartridge/thumb_1.png
pyvcmdline/template_0/cartridge/thumb_2.png
pyvcmdline/template_1/cartridge/__init__.py
pyvcmdline/template_1/cartridge/gamedef.py
pyvcmdline/template_1/cartridge/pimodules.py
pyvcmdline/template_1/cartridge/shared.py
pyvcmdline/template_1/cartridge/systems.py
pyvcmdline/template_1/cartridge/thumb_1.png
pyvcmdline/template_1/cartridge/thumb_2.png
pyvcmdline/template_1/cartridge/world.py
pyvcmdline/template_2/cartridge/World.py
pyvcmdline/template_2/cartridge/__init__.py
pyvcmdline/template_2/cartridge/classes.py
pyvcmdline/template_2/cartridge/gamedef.py
pyvcmdline/template_2/cartridge/my_map.ncsv
pyvcmdline/template_2/cartridge/pimodules.py
pyvcmdline/template_2/cartridge/shared.py
pyvcmdline/template_2/cartridge/systems.py
pyvcmdline/template_2/cartridge/thumb_1.png
pyvcmdline/template_2/cartridge/thumb_2.png
pyvcmdline/template_3/cartridge/ChessGUI_text.py
pyvcmdline/template_3/cartridge/ChessGameParams.py
pyvcmdline/template_3/cartridge/ChessmatchMod.py
pyvcmdline/template_3/cartridge/PythonChessAIStats.py
pyvcmdline/template_3/cartridge/ScrollingTextBox.py
pyvcmdline/template_3/cartridge/__init__.py
pyvcmdline/template_3/cartridge/ai_players.py
pyvcmdline/template_3/cartridge/black_bishop.png
pyvcmdline/template_3/cartridge/black_king.png
pyvcmdline/template_3/cartridge/black_knight.png
pyved_engine-24.9a1.dist-info/LICENSE
pyved_engine-24.9a1.dist-info/METADATA
pyved_engine-24.9a1.dist-info/WHEEL
pyved_engine-24.9a1.dist-info/entry_points.txt
pyved_engine-24.9a1.dist-info/top_level.txt
pyved_engine-24.9a1.dist-info/RECORD
