Metadata-Version: 2.1
Name: pyved-engine
Version: 24.9a1
Summary: Custom game engine built upon python/pygame
Home-page: https://github.com/gaudiatech/pyved-engine
Author: moonb3ndr et al.
Author-email: thomas.iw@kata.games
License: LGPL3
Keywords: Python,Pygame,Game Engine
License-File: LICENSE
Requires-Dist: pygame-ce >=2.2.1
Requires-Dist: pyperclip >=1.8.2
Requires-Dist: requests >=2.28.1
